pyrl_complete/__init__.py
pyrl_complete/apps/__init__.py
pyrl_complete/apps/notebook.py
pyrl_complete/apps/tester.py
pyrl_complete/common/string_utils.py
pyrl_complete/parser/.gitignore
pyrl_complete/parser/__init__.py
pyrl_complete/parser/parser.py
pyrl_complete/parser/rules.py
pyrl_complete/parser/tree.py
pyrl_complete-0.1.3.dist-info/LICENSE
pyrl_complete-0.1.3.dist-info/METADATA
pyrl_complete-0.1.3.dist-info/WHEEL
pyrl_complete-0.1.3.dist-info/entry_points.txt
pyrl_complete-0.1.3.dist-info/RECORD
