Metadata-Version: 2.3
Name: pyrl-complete
Version: 0.1.3
Summary: manage readline autocomplete for bespoke cli
License: GNU AFFERO GENERAL PUBLIC LICENSE Version 3
Keywords: readline,autocomplete,cli,ply
Author: codimoc
Author-email: codimoc@prismoid.uk
Requires-Python: >=3.9
Classifier: License :: Other/Proprietary License
Classifier: Programming Language :: Python :: 3
Classifier: Programming Language :: Python :: 3.9
Classifier: Programming Language :: Python :: 3.10
Classifier: Programming Language :: Python :: 3.11
Classifier: Programming Language :: Python :: 3.12
Classifier: Programming Language :: Python :: 3.13
Requires-Dist: ply (>=3.11,<4.0)
Project-URL: Repository, https://github.com/codimoc/pyrl-complete
